{"executedElements": "34.50", "elements": [{"executed": "Triple Twist Lift 2", "score": "6.30", "basevalue": "5.80", "goev": "0.50", "eldv": "\u00a0", "planned": "Triple Twist Lift"}, {"executed": "Triple Salchow", "score": "2.30", "basevalue": "4.40", "goev": "-2.10", "eldv": "\u00a0", "planned": "Triple Salchow"}, {"executed": "Throw Triple Salchow", "score": "3.70", "basevalue": "4.50", "goev": "-0.80", "eldv": "\u00a0", "planned": "Throw Triple Salchow"}, {"executed": "Fly. Change Foot Comb. Spin 4", "score": "4.00", "basevalue": "3.50", "goev": "0.50", "eldv": "\u00a0", "planned": "Fly. Change Foot Comb. Spin"}, {"executed": "Step Sequence 4", "score": "5.00", "basevalue": "3.90", "goev": "1.10", "eldv": "\u00a0", "planned": "Step Sequence"}, {"executed": "Group 5 Reverse Lasso Lift 4", "score": "8.30", "basevalue": "7.50", "goev": "0.80", "eldv": "\u00a0", "planned": "Group 5 Reverse Lasso Lift"}, {"executed": "Backward Inside Death Spiral 4", "score": "4.90", "basevalue": "3.50", "goev": "1.40", "eldv": "\u00a0", "planned": "Backward Inside Death Spiral"}], "elementsTotal": "34.50", "elementsBaseValueTotal": "33.10", "totalFactoredProgramComponents": "30.79", "deductions": [{"value": "0.00", "title": "Costume/Prop violation"}, {"value": "0.00", "title": "Time violation"}, {"value": "0.00", "title": "Illegal element/movement"}, {"value": "1.00", "title": "Falls"}, {"value": "0.00", "title": "Interruption in excess"}, {"value": "0.00", "title": "Costume failure"}, {"value": "0.00", "title": "Late start"}, {"value": "0.00", "title": "Violation of choreography restrictions"}], "score": "64.29", "components": [{"unfactoredScore": "7.68", "factor": "1.00", "title": "Skating Skills"}, {"unfactoredScore": "7.64", "factor": "1.00", "title": "Transitions"}, {"unfactoredScore": "7.54", "factor": "1.00", "title": "Performance"}, {"unfactoredScore": "7.89", "factor": "1.00", "title": "Composition"}, {"unfactoredScore": "7.75", "factor": "1.00", "title": "Interpretation of the Music"}], "totalDeductions": "1.00", "factoredProgramComponents": "30.79"}